mathfixer.py
proxy.py
mathfixer-1.0.1.dist-info/METADATA
mathfixer-1.0.1.dist-info/WHEEL
mathfixer-1.0.1.dist-info/entry_points.txt
mathfixer-1.0.1.dist-info/top_level.txt
mathfixer-1.0.1.dist-info/RECORD
