Metadata-Version: 2.1
Name: mathfixer
Version: 1.0.1
Summary: mathfixer, a tool for fixing math in MediaWiki-based wikis
Home-page: https://github.com/none-None1/mathfixer
Classifier: Operating System :: OS Independent
Classifier: Programming Language :: Python :: 3 :: Only
Requires-Dist: mitmproxy
Requires-Dist: bs4
